tests/__init__.py
tests/conftest.py
tests/test_decryption_utils.py
tests/test_exceptions.py
tests/test_factory.py
tests/test_main.py
tests/test_step_implementer.py
tests/test_step_result.py
tests/test_workflow_result.py
tests/helpers/__init__.py
tests/helpers/base_step_implementer_test_case.py
tests/helpers/base_tssc_test_case.py
tests/helpers/maven_step_implementer_test_case.py
tests/helpers/sample_step_implementers.py
tests/helpers/sops_integration_test_case.py
tests/helpers/test_utils.py
tssc/__init__.py
tssc/__main__.py
tssc/decryption_utils.py
tssc/exceptions.py
tssc/factory.py
tssc/step_implementer.py
tssc/step_result.py
tssc/version.py
tssc/workflow_result.py
tssc/config/__init__.py
tssc/config/config.py
tssc/config/config_value.py
tssc/config/config_value_decryptor.py
tssc/config/step_config.py
tssc/config/sub_step_config.py
tssc/config/decryptors/__init__.py
tssc/config/decryptors/sops.py
tssc/step_implementers/__init__.py
tssc/step_implementers/container_image_static_compliance_scan/__init__.py
tssc/step_implementers/container_image_static_compliance_scan/openscap.py
tssc/step_implementers/container_image_static_vulnerability_scan/__init__.py
tssc/step_implementers/container_image_static_vulnerability_scan/openscap.py
tssc/step_implementers/create_container_image/__init__.py
tssc/step_implementers/create_container_image/buildah.py
tssc/step_implementers/deploy/__init__.py
tssc/step_implementers/deploy/argocd.py
tssc/step_implementers/generate_metadata/__init__.py
tssc/step_implementers/generate_metadata/git.py
tssc/step_implementers/generate_metadata/maven.py
tssc/step_implementers/generate_metadata/npm.py
tssc/step_implementers/generate_metadata/semantic_version.py
tssc/step_implementers/package/__init__.py
tssc/step_implementers/package/maven.py
tssc/step_implementers/push_artifacts/__init__.py
tssc/step_implementers/push_artifacts/maven.py
tssc/step_implementers/push_container_image/__init__.py
tssc/step_implementers/push_container_image/skopeo.py
tssc-0.15.0.dist-info/COMMITMENT
tssc-0.15.0.dist-info/LICENSE
tssc-0.15.0.dist-info/METADATA
tssc-0.15.0.dist-info/WHEEL
tssc-0.15.0.dist-info/top_level.txt
tssc-0.15.0.dist-info/RECORD
